lcSV/__init__.py
lcSV/compute.py
lcSV/evaluate.py
lcSV/model.py
lcSV/nonahore.py
lcSV/plot.py
lcSV/process.py
lcSV/read.py
lcSV/simulate.py
lcsvpy-0.0.1.dist-info/METADATA
lcsvpy-0.0.1.dist-info/WHEEL
lcsvpy-0.0.1.dist-info/licenses/LICENSE
lcsvpy-0.0.1.dist-info/RECORD
