Metadata-Version: 2.4
Name: lcSVpy
Version: 0.0.1
Summary: Low-coverage structural variant (lcSV)
Project-URL: Source, https://github.com/Suuuuuuuus/lcSV/
Project-URL: Issues, https://github.com/Suuuuuuuus/lcSV/issues
Author-email: Sus <bjzzp01@163.com>
License: Copyright 2025, Sus
License-File: LICENSE
Classifier: Operating System :: OS Independent
Classifier: Programming Language :: Python :: 3
Requires-Python: >=3.8
Requires-Dist: matplotlib>=3.4
Requires-Dist: numpy
Requires-Dist: pandas>=1.2
Requires-Dist: scipy
Requires-Dist: seaborn
Requires-Dist: statsmodels
Provides-Extra: dev
Requires-Dist: flit; extra == 'dev'
Requires-Dist: mypy; extra == 'dev'
Requires-Dist: pytest; extra == 'dev'
Provides-Extra: stats
Requires-Dist: scipy>=1.7; extra == 'stats'
Requires-Dist: statsmodels>=0.12; extra == 'stats'
